ProtonDBclient/ProtonDBclient.py
ProtonDBclient/ProtonRequest.py
ProtonDBclient/ProtonResponse.py
ProtonDBclient/__init__.py
ProtonDBclient/connection.py
ProtonDBclient/protondbdriver.py
protondbclient-0.1.2.dist-info/METADATA
protondbclient-0.1.2.dist-info/WHEEL
protondbclient-0.1.2.dist-info/top_level.txt
protondbclient-0.1.2.dist-info/RECORD
