Metadata-Version: 2.4
Name: ProtonDBclient
Version: 0.1.2
Summary: Python wrapper for ProtonDB, a custom TCP-based NoSQL database
Author-email: Sarvesh <sarveshjrgar@gmail.com>
Project-URL: Homepage, https://github.com/sarveshsarvs/ProtonDB
Project-URL: Repository, https://github.com/sarveshsarvs/ProtonDB/tree/master/Wrapper/pyproton
Requires-Python: >=3.7
